{"cameraMode":{"drawMode":0,"name":"Shaded","section":"Shading Mode"},"sceneLighting":false,"audioPlay":false,"sceneViewState":{"m_AlwaysRefresh":false,"showFog":true,"showSkybox":false,"showFlares":true,"showImageEffects":true,"showParticleSystems":true,"showVisualEffectGraphs":true,"m_FxEnabled":true},"in2DMode":false,"pivot":{"x":15.820155143737793,"y":1.0493738651275635,"z":11.287787437438965},"rotation":{"x":0.14017848670482636,"y":-0.7130206823348999,"z":0.14910700917243958,"w":0.6706743240356445},"size":0.34640997648239138,"orthographic":false}